Metadata-Version: 2.1
Name: TestPypiIonut
Version: 0.1
Summary: Do not install
Home-page: UNKNOWN
Author: Bucur Ionut
Author-email: random@random.com
License: UNKNOWN
Keywords: do,not,use
Platform: UNKNOWN
Classifier: Development Status :: 3 - Alpha
Classifier: Programming Language :: Python :: 3.9
